zhangyx_test_1/__init__.py
zhangyx_test_1/mytest.py
zhangyx_test_1/test.py
zhangyx_test_1-0.20.dist-info/METADATA
zhangyx_test_1-0.20.dist-info/WHEEL
zhangyx_test_1-0.20.dist-info/top_level.txt
zhangyx_test_1-0.20.dist-info/RECORD
