Metadata-Version: 2.1
Name: zhangyx-test-1
Version: 0.20
Summary: My test module
Home-page: http://www.csdn.net
Author: Zhang Yexing
Author-email: 1207979407@qq.com
License: LGPL
Platform: UNKNOWN
